{
  "realm": "pengadilan-agama",
  "enabled": true,
  "sslRequired": "external",
  "registrationAllowed": false,
  "loginWithEmailAllowed": true,
  "duplicateEmailsAllowed": false,
  "resetPasswordAllowed": true,
  "editUsernameAllowed": false,
  "bruteForceProtected": true,
  "bruteForceMaxLoginFailures": 5,
  "bruteForceWaitIncrementSeconds": 30,
  "browserSecurityHeaders": {
    "contentSecurityPolicyReportOnly": "",
    "xContentTypeOptions": "nosniff",
    "xRobotsTag": "none",
    "xFrameOptions": "SAMEORIGIN",
    "xXSSProtection": "1; mode=block",
    "strictTransportSecurity": "max-age=31536000; includeSubDomains"
  },
  "smtpServer": {},
  "attributes": {
    "access.token.lifespan": "900",
    "sso.session.max.lifespan": "86400",
    "sso.session.idle.lifespan": "86400",
    "refresh.token.max.reuse": "0"
  },
  "userManagedAccessAllowed": false,
  "adminEventsEnabled": true,
  "adminEventsDetailsEnabled": true,
  "eventsEnabled": true,
  "eventsListeners": ["jboss-logging"],
  "eventsExpiration": 604800,
  "internationalizationEnabled": true,
  "supportedLocales": ["id", "en"],
  "defaultLocale": "id",
  "browserFlow": "browser",
  "registrationFlow": "registration",
  "directGrantFlow": "direct grant",
  "resetCredentialsFlow": "reset credentials",
  "clientAuthenticationFlow": "clients",
  "dockerAuthenticationFlow": "docker auth",
  "firstBrokerLoginFlow": "first broker login",
  "offlineSession": "offline",
  "roles": {
    "realm": [
      {
        "name": "admin",
        "description": "Administrator dengan akses penuh",
        "composite": false,
        "clientRole": false,
        "containerId": null,
        "attributes": {}
      },
      {
        "name": "supervisor",
        "description": "Supervisor dengan akses terbatas untuk approval",
        "composite": false,
        "clientRole": false,
        "containerId": null,
        "attributes": {}
      },
      {
        "name": "officer",
        "description": "Officer dengan akses operasional",
        "composite": false,
        "clientRole": false,
        "containerId": null,
        "attributes": {}
      },
      {
        "name": "staff",
        "description": "Staff dengan akses dasar",
        "composite": false,
        "clientRole": false,
        "containerId": null,
        "attributes": {}
      },
      {
        "name": "user",
        "description": "User dengan akses read-only",
        "composite": false,
        "clientRole": false,
        "containerId": null,
        "attributes": {}
      }
    ],
    "client": {}
  },
  "groups": [],
  "defaultRoles": ["user"],
  "requiredCredentials": ["password"],
  "otpPolicyType": "totp",
  "otpPolicyAlgorithm": "HmacSHA1",
  "otpPolicyInitialCounter": 0,
  "otpPolicyDigits": 6,
  "otpPolicyLookAheadWindow": 1,
  "otpPolicyPeriod": 30,
  "otpSupportedApplications": ["FreeOTP", "Google Authenticator"],
  "webAuthnPolicyRpEntityName": "keycloak",
  "webAuthnPolicySignatureAlgorithms": ["ES256"],
  "webAuthnPolicyRpId": "",
  "webAuthnPolicyAttestationConveyancePreference": "not specified",
  "webAuthnPolicyRequireResidentKey": "not specified",
  "webAuthnPolicyUserVerificationRequirement": "not specified",
  "webAuthnPolicyCreateTimeout": 0,
  "webAuthnPolicyAvoidSameAuthenticatorRegister": false,
  "webAuthnPolicyAcceptableAaguids": [],
  "clients": [
    {
      "clientId": "portal-client",
      "name": "Portal SIKERMA",
      "enabled": true,
      "clientAuthenticatorType": "client-secret",
      "secret": "portal-secret-change-in-production",
      "redirectUris": [
        "http://localhost:3000/*",
        "http://localhost:3000/auth/callback/*"
      ],
      "webOrigins": ["http://localhost:3000"],
      "bearerOnly": false,
      "consentRequired": false,
      "standardFlowEnabled": true,
      "implicitFlowEnabled": false,
      "directAccessGrantsEnabled": false,
      "serviceAccountsEnabled": false,
      "publicClient": false,
      "protocol": "openid-connect",
      "attributes": {
        "access.token.lifespan": "900"
      },
      "authenticationFlowBindingOverrides": {},
      "fullScopeAllowed": true,
      "nodeReRegistrationTimeout": -1,
      "protocolMappers": [
        {
          "name": "audience resolve",
          "protocol": "openid-connect",
          "protocolMapper": "oidc-audience-resolve-mapper",
          "consentRequired": false,
          "config": {}
        },
        {
          "name": "name",
          "protocol": "openid-connect",
          "protocolMapper": "oidc-usermodel-property-mapper",
          "consentRequired": false,
          "config": {
            "userinfo.token.claim": "true",
            "user.attribute": "name",
            "id.token.claim": "true",
            "access.token.claim": "true",
            "claim.name": "name",
            "jsonType.label": "String"
          }
        },
        {
          "name": "preferred_username",
          "protocol": "openid-connect",
          "protocolMapper": "oidc-usermodel-property-mapper",
          "consentRequired": false,
          "config": {
            "userinfo.token.claim": "true",
            "user.attribute": "username",
            "id.token.claim": "true",
            "access.token.claim": "true",
            "claim.name": "preferred_username",
            "jsonType.label": "String"
          }
        },
        {
          "name": "email",
          "protocol": "openid-connect",
          "protocolMapper": "oidc-usermodel-property-mapper",
          "consentRequired": false,
          "config": {
            "userinfo.token.claim": "true",
            "user.attribute": "email",
            "id.token.claim": "true",
            "access.token.claim": "true",
            "claim.name": "email",
            "jsonType.label": "String"
          }
        },
        {
          "name": "realm roles",
          "protocol": "openid-connect",
          "protocolMapper": "oidc-usermodel-realm-role-mapper",
          "consentRequired": false,
          "config": {
            "multivalued": "true",
            "userinfo.token.claim": "true",
            "id.token.claim": "true",
            "access.token.claim": "true",
            "claim.name": "roles",
            "jsonType.label": "String",
            "claim.value.prefix": ""
          }
        }
      ]
    },
    {
      "clientId": "master-data-client",
      "name": "Master Data SIKERMA",
      "enabled": true,
      "clientAuthenticatorType": "client-secret",
      "secret": "master-data-secret-change-in-production",
      "redirectUris": [
        "http://localhost:3001/*",
        "http://localhost:3001/auth/callback/*"
      ],
      "webOrigins": ["http://localhost:3001"],
      "bearerOnly": false,
      "consentRequired": false,
      "standardFlowEnabled": true,
      "implicitFlowEnabled": false,
      "directAccessGrantsEnabled": false,
      "serviceAccountsEnabled": false,
      "publicClient": false,
      "protocol": "openid-connect",
      "attributes": {
        "access.token.lifespan": "900"
      },
      "authenticationFlowBindingOverrides": {},
      "fullScopeAllowed": true,
      "nodeReRegistrationTimeout": -1,
      "protocolMappers": [
        {
          "name": "audience resolve",
          "protocol": "openid-connect",
          "protocolMapper": "oidc-audience-resolve-mapper",
          "consentRequired": false,
          "config": {}
        },
        {
          "name": "name",
          "protocol": "openid-connect",
          "protocolMapper": "oidc-usermodel-property-mapper",
          "consentRequired": false,
          "config": {
            "userinfo.token.claim": "true",
            "user.attribute": "name",
            "id.token.claim": "true",
            "access.token.claim": "true",
            "claim.name": "name",
            "jsonType.label": "String"
          }
        },
        {
          "name": "preferred_username",
          "protocol": "openid-connect",
          "protocolMapper": "oidc-usermodel-property-mapper",
          "consentRequired": false,
          "config": {
            "userinfo.token.claim": "true",
            "user.attribute": "username",
            "id.token.claim": "true",
            "access.token.claim": "true",
            "claim.name": "preferred_username",
            "jsonType.label": "String"
          }
        },
        {
          "name": "email",
          "protocol": "openid-connect",
          "protocolMapper": "oidc-usermodel-property-mapper",
          "consentRequired": false,
          "config": {
            "userinfo.token.claim": "true",
            "user.attribute": "email",
            "id.token.claim": "true",
            "access.token.claim": "true",
            "claim.name": "email",
            "jsonType.label": "String"
          }
        },
        {
          "name": "realm roles",
          "protocol": "openid-connect",
          "protocolMapper": "oidc-usermodel-realm-role-mapper",
          "consentRequired": false,
          "config": {
            "multivalued": "true",
            "userinfo.token.claim": "true",
            "id.token.claim": "true",
            "access.token.claim": "true",
            "claim.name": "roles",
            "jsonType.label": "String",
            "claim.value.prefix": ""
          }
        }
      ]
    },
    {
      "clientId": "kepegawaian-client",
      "name": "Kepegawaian SIKERMA",
      "enabled": true,
      "clientAuthenticatorType": "client-secret",
      "secret": "kepegawaian-secret-change-in-production",
      "redirectUris": [
        "http://localhost:3002/*",
        "http://localhost:3002/auth/callback/*"
      ],
      "webOrigins": ["http://localhost:3002"],
      "bearerOnly": false,
      "consentRequired": false,
      "standardFlowEnabled": true,
      "implicitFlowEnabled": false,
      "directAccessGrantsEnabled": false,
      "serviceAccountsEnabled": false,
      "publicClient": false,
      "protocol": "openid-connect",
      "attributes": {
        "access.token.lifespan": "900"
      },
      "authenticationFlowBindingOverrides": {},
      "fullScopeAllowed": true,
      "nodeReRegistrationTimeout": -1,
      "protocolMappers": [
        {
          "name": "audience resolve",
          "protocol": "openid-connect",
          "protocolMapper": "oidc-audience-resolve-mapper",
          "consentRequired": false,
          "config": {}
        },
        {
          "name": "name",
          "protocol": "openid-connect",
          "protocolMapper": "oidc-usermodel-property-mapper",
          "consentRequired": false,
          "config": {
            "userinfo.token.claim": "true",
            "user.attribute": "name",
            "id.token.claim": "true",
            "access.token.claim": "true",
            "claim.name": "name",
            "jsonType.label": "String"
          }
        },
        {
          "name": "preferred_username",
          "protocol": "openid-connect",
          "protocolMapper": "oidc-usermodel-property-mapper",
          "consentRequired": false,
          "config": {
            "userinfo.token.claim": "true",
            "user.attribute": "username",
            "id.token.claim": "true",
            "access.token.claim": "true",
            "claim.name": "preferred_username",
            "jsonType.label": "String"
          }
        },
        {
          "name": "email",
          "protocol": "openid-connect",
          "protocolMapper": "oidc-usermodel-property-mapper",
          "consentRequired": false,
          "config": {
            "userinfo.token.claim": "true",
            "user.attribute": "email",
            "id.token.claim": "true",
            "access.token.claim": "true",
            "claim.name": "email",
            "jsonType.label": "String"
          }
        },
        {
          "name": "realm roles",
          "protocol": "openid-connect",
          "protocolMapper": "oidc-usermodel-realm-role-mapper",
          "consentRequired": false,
          "config": {
            "multivalued": "true",
            "userinfo.token.claim": "true",
            "id.token.claim": "true",
            "access.token.claim": "true",
            "claim.name": "roles",
            "jsonType.label": "String",
            "claim.value.prefix": ""
          }
        }
      ]
    },
    {
      "clientId": "backend-api",
      "name": "Backend API",
      "enabled": true,
      "clientAuthenticatorType": "client-secret",
      "secret": "backend-api-secret-change-in-production",
      "redirectUris": [],
      "webOrigins": [],
      "bearerOnly": true,
      "consentRequired": false,
      "standardFlowEnabled": false,
      "implicitFlowEnabled": false,
      "directAccessGrantsEnabled": false,
      "serviceAccountsEnabled": true,
      "publicClient": false,
      "protocol": "openid-connect",
      "attributes": {},
      "authenticationFlowBindingOverrides": {},
      "fullScopeAllowed": true,
      "nodeReRegistrationTimeout": -1
    }
  ],
  "users": [
    {
      "username": "admin",
      "enabled": true,
      "emailVerified": true,
      "email": "admin@sikerma.go.id",
      "firstName": "Admin",
      "lastName": "Sikerma",
      "credentials": [
        {
          "type": "password",
          "value": "admin123",
          "temporary": false
        }
      ],
      "realmRoles": ["admin", "offline_access"],
      "clientRoles": {},
      "groups": []
    },
    {
      "username": "supervisor",
      "enabled": true,
      "emailVerified": true,
      "email": "supervisor@sikerma.go.id",
      "firstName": "Supervisor",
      "lastName": "Sikerma",
      "credentials": [
        {
          "type": "password",
          "value": "supervisor123",
          "temporary": false
        }
      ],
      "realmRoles": ["supervisor", "offline_access"],
      "clientRoles": {},
      "groups": []
    },
    {
      "username": "officer",
      "enabled": true,
      "emailVerified": true,
      "email": "officer@sikerma.go.id",
      "firstName": "Officer",
      "lastName": "Sikerma",
      "credentials": [
        {
          "type": "password",
          "value": "officer123",
          "temporary": false
        }
      ],
      "realmRoles": ["officer", "offline_access"],
      "clientRoles": {},
      "groups": []
    },
    {
      "username": "staff",
      "enabled": true,
      "emailVerified": true,
      "email": "staff@sikerma.go.id",
      "firstName": "Staff",
      "lastName": "Sikerma",
      "credentials": [
        {
          "type": "password",
          "value": "staff123",
          "temporary": false
        }
      ],
      "realmRoles": ["staff", "offline_access"],
      "clientRoles": {},
      "groups": []
    }
  ],
  "scopeMappings": [],
  "clientScopeMappings": {},
  "clientScopes": [],
  "defaultDefaultClientScopes": [
    "profile",
    "email",
    "roles",
    "web-origins",
    "acr",
    "role_list",
    "offline_access"
  ],
  "defaultOptionalClientScopes": [
    "address",
    "phone",
    "microprofile-jwt",
    "organization"
  ]
}